Metadata-Version: 2.1
Name: igsr-analysis
Version: 1.1.1
Summary: Code that is relevant for the analysis (Mapping, BAM qc, Variant Calling, Filtering etc...) of IGSR data
Home-page: https://github.com/igsr/igsr_analysis
Author: Ernesto Lowy
Author-email: ernestolowy@gmail.com
License: Apache License 2.0
Platform: UNKNOWN
Requires-Dist: pandas
Requires-Dist: PyMySQL
Requires-Dist: scipy
Requires-Dist: numpy
Requires-Dist: matplotlib
Requires-Dist: matplotlib-venn
